flap/__init__.py
flap/alignment/__init__.py
flap/alignment/linear_assignment_alignment.py
flap/api/__init__.py
flap/api/database_setup.py
flap/api/match.py
flap/api/score.py
flap/api/score_and_match.py
flap/database/__init__.py
flap/database/db_build_vocabulary.py
flap/database/db_import.py
flap/database/db_index.py
flap/database/sql.py
flap/database/sql_in_memory.py
flap/evaluation/__init__.py
flap/matcher/__init__.py
flap/matcher/sql_matcher.py
flap/model/__init__.py
flap/parser/__init__.py
flap/parser/multiplier_index.csv
flap/parser/pc1_mappings_region.json
flap/parser/rule_parser_fast.py
flap/parser/thoroughfare_patterns.json
flap/preprocessing/__init__.py
flap/utils/__init__.py
flap/utils/cpu_count.py
flap/utils/progress_map.py
flap_lite-0.6.27.dist-info/LICENSE
flap_lite-0.6.27.dist-info/METADATA
flap_lite-0.6.27.dist-info/WHEEL
flap_lite-0.6.27.dist-info/top_level.txt
flap_lite-0.6.27.dist-info/RECORD
